gps_anomaly/__init__.py
gps_anomaly/config/distance.py
gps_anomaly/config/heading.py
gps_anomaly/config/info_anomalies.py
gps_anomaly/detect_functions.py
gps_anomaly/detector.py
gps_anomaly/one_sequence.py
gps_anomaly-0.1.14.dist-info/METADATA
gps_anomaly-0.1.14.dist-info/WHEEL
gps_anomaly-0.1.14.dist-info/RECORD
