Metadata-Version: 2.1
Name: gps-anomaly
Version: 0.1.14
Summary: Detecet and Remove GPS anomalies points
Author: mcv_
Author-email: murat@visiosoft.com.tr
Requires-Python: >=3.7,<4.0
Classifier: Programming Language :: Python :: 3
Classifier: Programming Language :: Python :: 3.7
Classifier: Programming Language :: Python :: 3.8
Classifier: Programming Language :: Python :: 3.9
Classifier: Programming Language :: Python :: 3.10
Classifier: Programming Language :: Python :: 3.11
